image_processing/__init__.py
image_processing/processing/__init__.py
image_processing/processing/combination.py
image_processing/processing/transformation.py
image_processing/utils/__init__.py
image_processing/utils/io.py
image_processing/utils/plot.py
processador_imagem/__init__.py
processador_imagem/processando/__init__.py
processador_imagem/processando/combinacao.py
processador_imagem/processando/transformacao.py
processador_imagem/util/__init__.py
processador_imagem/util/io.py
processador_imagem/util/plot.py
processador_imagem_virtual/__init__.py
processador_imagem_virtual/processando/__init__.py
processador_imagem_virtual/processando/combinacao.py
processador_imagem_virtual/processando/transformacao.py
processador_imagem_virtual/util/__init__.py
processador_imagem_virtual/util/io.py
processador_imagem_virtual/util/plot.py
processador_imagem_virtual-0.0.5.dist-info/METADATA
processador_imagem_virtual-0.0.5.dist-info/WHEEL
processador_imagem_virtual-0.0.5.dist-info/top_level.txt
processador_imagem_virtual-0.0.5.dist-info/RECORD
