Metadata-Version: 2.1
Name: processador-imagem-virtual
Version: 0.0.5
Summary: Pacote de processamento de imagem usando Skimage
Home-page: https://github.com/ubiratan-motta/Processador_de_Imagens
Author: Ubiratan Motta
Author-email: mottaubiratan@gmail.com
License: UNKNOWN
Platform: UNKNOWN
Requires-Python: >=3.8
Requires-Dist: matplotlib
Requires-Dist: numpy
Requires-Dist: scikit-image (>=0.16.1)
